<?xml version="1.0" encoding="UTF-8" standalone="yes"?>
<post>
    <author>나수환</author>
    <comments/>
    <content>닷넷에 관하여 공부를 했는데, 혹, 다시 한번 그러한 계획이 있는지요?&lt;br&gt;그리고, 닷넷 교육 자료를 다운받을수 있는지요?&lt;br&gt;다운 받지 못한다면 저의 이메일로 부탁 드리고 싶읍니다.&lt;br&gt;&lt;br&gt;현재 닷넷으로 제품의 일부분이 개발중이랍니다. 개인적으로 준비를 하고 하여 이렇게 코스카에 자료및 세미나를 문의 합니다.&lt;br&gt;&lt;br&gt;alexna2003@yahoo.com</content>
    <postId>C0402B38-18FD-4427-96CC-4C404B707CF8</postId>
    <pubDate>2005-02-23T00:00:00-05:00</pubDate>
    <title>.Net 공부</title>
</post>
