<?xml version="1.0" encoding="UTF-8" standalone="yes"?>
<post>
    <author>권칠환</author>
    <comments/>
    <content>We're currently working with an established software development and IT consulting firm in Bermuda, seeking a Senior .NET Developer to join their team on the Island. &lt;br&gt;&lt;br&gt;Relocation assistance, health benefits and a competitive and nearly completely tax-free (4.75% tax) compensation package will be offered to the successful candidate. As well, it would be extremely helpful if you have outside interests that lend themselves to this beautiful and idyllic living environment. &lt;br&gt;&lt;br&gt; &lt;br&gt;&lt;br&gt;I've attached details of the role for your review. If this is something you would be interested in exploring, I'd be happy to speak in detail.&lt;br&gt;&lt;br&gt; &lt;br&gt;Thanks Chilhoan,&lt;br&gt;&lt;br&gt;Jessica Poulsen&lt;br&gt;Squires Resources Inc.&lt;br&gt;705.725.7660 ext. 22&lt;br&gt;877.435.0921 toll free from Toronto&lt;br&gt;jessica@squiresresources.com&lt;br&gt;www.squiresresources.com&lt;br&gt;Become a Fan of Squires Resources on Facebook &lt;br&gt;</content>
    <postId>3B757B98-FDDA-4601-99BD-80C3BBDA54C3</postId>
    <pubDate>2009-08-26T00:00:00-04:00</pubDate>
    <title>Senior .NET Developer Opportunity</title>
</post>
