<?xml version="1.0" encoding="UTF-8" standalone="yes"?>
<post>
    <author>이병운</author>
    <comments>
        <comment>
            <author>권칠환</author>
            <date>2005-09-29T00:00:00-04:00</date>
            <content>상대방 요구사항 잘 알아듣고, 쓰기는 듣기 보다나으면, 말하기는 머리에서 문장만들어서 입으로 전달하는데 약 10-20초정도 걸립니다. 말 만드는동안.."hmm"을 몇번합니다.</content>
        </comment>
        <comment>
            <author>허현옥</author>
            <date>2005-09-29T00:00:00-04:00</date>
            <content>전 아직 미취업입니다만...캐나다와서 가장 힘든 건 다국적 국민들이 살고 있다는 겁니다. 처음에는 우리집에 배달온 사람들말이 뭔소린지 전혀 못알아 들었답니다.그사람들은 대부분...</content>
        </comment>
    </comments>
    <content>안녕하세요? 이병운입니다.&lt;br&gt;내년 10월로 랜딩시기를 결정하였습니다. 다만 그것이 임시 랜딩이 될지&lt;br&gt;영구 랜딩이 될지는 아직 결정하지 못하였습니다. 저는 현재 한국에서&lt;br&gt;아케이드 게임을 개발하는 프로그래머입니다.&lt;br&gt;&lt;br&gt;아래에 취업에 성공하신분들의 글을 보니 마치 제가 취업에 성공한거 처럼&lt;br&gt;기쁩니다. 조건과 환경은 다르겠지만 저도 그럴수 있을거라는 희망같은게&lt;br&gt;보입니다.&lt;br&gt;&lt;br&gt;전에도 많은 분들이 영어에 대한 중요성을 조언해 주셨지만 한국에서&lt;br&gt;직장생활을 하다보니 영어를 공부하겠다는 의지만 있지 실질적인 것은&lt;br&gt;항상 제자리 인것 같습니다.&lt;br&gt;&lt;br&gt;그래서 궁금한것이 있는데요.&lt;br&gt;취업에 성공하신 분들의 영어능력은 어느정도인신가요? 기본적인&lt;br&gt;회화를 비롯해서 읽기 쓰기 등등 어느정도 수준이신지 궁금합니다.&lt;br&gt;&lt;br&gt;질문해 놓고 보니까 좀 질문이 좀 우스워 졌네요... ^^;;;&lt;br&gt;취업을 위한 영어의 데드라인이라고 할까요? 조언 부탁드립니다.&lt;br&gt;&lt;br&gt;그럼 미리 감사드립니다.&lt;br&gt;&lt;br&gt;이병운&lt;br&gt;</content>
    <postId>5390B0C2-EEEF-41F1-9B28-179CD134BECD</postId>
    <pubDate>2005-09-29T00:00:00-04:00</pubDate>
    <title>가끔씩 들러서 질문만하고 가네요 ^^; 이번에도 질문있습니다.</title>
</post>
