<?xml version="1.0" encoding="UTF-8" standalone="yes"?>
<post>
    <author>Youn</author>
    <comments/>
    <content>안녕하세요. &lt;br&gt;&lt;br&gt;이번 여름 학기에 Co-op job을 찾고 있습니다.&lt;br&gt;&lt;br&gt;학교 과정 중에 포함되어 있는데, 학교 서비스로는 쉽지 않네요. &lt;br&gt;&lt;br&gt;제 조건은,&lt;br&gt;&lt;br&gt;5월 부터 8월 말 사이에, 360시간 이상 IT 관련 업체에서 일 해야 합니다.&lt;br&gt;&lt;br&gt;학교에서는 언어로 C, VB, Java 를 배웠고,&lt;br&gt;&lt;br&gt;DB, Oracle, O/S, Network 정도...&lt;br&gt;&lt;br&gt;그 외에 Visual C++, ASP 기본 수준 정도 입니다.&lt;br&gt;&lt;br&gt;혹시 정보 가지고 계신 분이나, 관심 있으신 분들은 연락 부탁드립니다.&lt;br&gt;&lt;br&gt;karahan0@nate.com</content>
    <postId>7C6B4B84-6339-4C60-92D4-11275FB5F90D</postId>
    <pubDate>2005-04-05T00:00:00-04:00</pubDate>
    <title>Looking for Co-op job</title>
</post>
