<?xml version="1.0" encoding="UTF-8" standalone="yes"?>
<post>
    <author>Mike Lee</author>
    <comments/>
    <content>안녕하세여.&lt;br&gt;이민온지 이제 2주되었습니다. 다른 것은 어느정도 정리가 되었고 이제 가장 중요한 잡을 찾고있는 데요. 저는 최근 미국에서 컴퓨터 사이언스 석사학위를&amp;nbsp;&amp;nbsp;취득하였고 같은 학교에서 수업조교 (speaking English in the class) 를 1년반 하엿습니다. 따라서 학원 강사를 포함, 소프트웨어관련 어떤직종 이라도 시작하려 하나 경험이 적은것이 가장 큰 걸림돌입니다. 제가 수업조교한것이 프로그래밍 쪽인데(자바 , 오라클) 이와 관련되어&amp;nbsp;&amp;nbsp;제가 잡을 잡는데 조언부탁드립니다 .&lt;br&gt;&lt;br&gt;한가지 더 -&amp;gt; 저도 COSKA에서 자원봉사자가 될수있나요?&amp;nbsp;&amp;nbsp;&amp;nbsp;&amp;nbsp;&amp;nbsp;&amp;nbsp;&amp;nbsp;&amp;nbsp;</content>
    <postId>FDA716AD-1887-4B39-BFF7-845563A452D1</postId>
    <pubDate>2002-01-24T00:00:00-05:00</pubDate>
    <title>A Question</title>
</post>
