<?xml version="1.0" encoding="UTF-8" standalone="yes"?>
<post>
    <author>오승준</author>
    <comments/>
    <content>오랫만에 많은분들이 오셨습니다...&lt;br&gt;덕분에 술도 많이 마시고, 사진기 잃어서 섭섭했던 마음이 싸~악 지워졌습니다.ㅋㅋㅋ&lt;br&gt;하지만 이로인해 저의 멍청함이 모든 코스카회원들에게 알려져서 좀 그렇습니다..ㅜㅜ&lt;br&gt;&lt;br&gt;암튼 즐거운 시간이었고, 나와주신 많은분들과, 특히 김세환 전회장님께 감사드립니다.&lt;br&gt;&lt;br&gt;&lt;br&gt;&lt;br&gt;P.S. 어제 오셨던분들 모두 피크닉에도 꼭 오세요.&lt;br&gt;&lt;br&gt;&lt;br&gt;&amp;gt;때 :&amp;nbsp;&amp;nbsp;&amp;nbsp;&amp;nbsp;이번 주 목요일...6월 1일&amp;nbsp;&amp;nbsp;저녁 7:00 PM 정도에 시작...&lt;br&gt;&amp;gt;&amp;nbsp;&amp;nbsp;&amp;nbsp;&amp;nbsp;&amp;nbsp;&amp;nbsp;&amp;nbsp;&amp;nbsp; &lt;br&gt;&amp;gt;장소:&amp;nbsp;&amp;nbsp;FERG'S&amp;nbsp;&amp;nbsp;5254 Yonge St.&amp;nbsp;&amp;nbsp; Tel 416-224-2196&lt;br&gt;&amp;gt;&amp;nbsp;&amp;nbsp;&amp;nbsp;&amp;nbsp;&amp;nbsp;&amp;nbsp;&amp;nbsp;&amp;nbsp; ( North York 부엉이식당있는곳에서 1 Block 남쪽 코너)&lt;br&gt;&amp;gt;&lt;br&gt;&amp;gt;그럼 부담없이 얼굴들 한번봅시다....감사...&lt;br&gt;</content>
    <postId>97A8B568-C378-409C-9C28-189E43582C97</postId>
    <pubDate>2006-06-02T00:00:00-04:00</pubDate>
    <title>[re] 꼭 뜻이 그러시면..그냥 번개합시다...(Revised information)</title>
</post>
