<?xml version="1.0" encoding="UTF-8" standalone="yes"?>
<post>
    <author>허현옥</author>
    <comments>
        <comment>
            <author>Sonia</author>
            <date>2006-03-23T00:00:00-05:00</date>
            <content>남아서 처리가 곤란할정도로 여유는 없지만, 제가 사용하지 안는것 하나는 드릴수 있습니다. 몇개가 필요하시고, 길이는 얼마면 되는지요?</content>
        </comment>
        <comment>
            <author>허현옥</author>
            <date>2006-03-23T00:00:00-05:00</date>
            <content>1~2면 됩니다. 길이는 그렇게 길지 않아도 됩니다.1~2m면 충분 할듯 하네요...감사! 또 감사 합니다-_ㅜ</content>
        </comment>
        <comment>
            <author>Sonia</author>
            <date>2006-03-23T00:00:00-05:00</date>
            <content>어떻게 드리면 되죠? 제 연락처는 416-908-5457입니다.</content>
        </comment>
        <comment>
            <author>허현옥</author>
            <date>2006-03-23T00:00:00-05:00</date>
            <content>혹시 Coska 총회에 안오시나요? 오시면 거기서 주시면 될 것 같구요. 안되면 제가 전화를 드리고 만나도 될거 같구요.^^</content>
        </comment>
        <comment>
            <author>허현옥</author>
            <date>2006-03-24T00:00:00-05:00</date>
            <content>전화드렸는데.. 전화 안되고 메시지는 꽉찼다고 나오네요..^^ 괜찮으시면 416-241-1210으로 전화부탁드려요. 응답기로 스크리닝하니까 말씀하시면 제가 받을 겁니다.^^</content>
        </comment>
    </comments>
    <content>한국에서는 네트웍케이블 아무리 비싸도 2000원이면 샀는데,&lt;br&gt;그리고 대부분 회사에 네트웍케이블 만드는 장비정도는 있어서,&lt;br&gt;필요하면 그냥 만들어 쓸 수도 있엇는데..여기는 상당히 비싸군요.&lt;br&gt;&lt;br&gt;제가 가개를 잘 못 찾아서 그런 건지 대부분 7~8불 정도 하네요.&lt;br&gt;&lt;br&gt;혹시 집이나 회사에 네트웍 케이블이 남아서 처치 곤란이신 분계시면&lt;br&gt;제가 처리(?) 해드리겠습니다..-_ㅜ&lt;br&gt;&lt;br&gt;미리 감사 드려요~</content>
    <postId>9907DAE0-9D3A-4F8D-A225-82F8175D27BE</postId>
    <pubDate>2006-03-23T00:00:00-05:00</pubDate>
    <title>혹시 네트웍 케이블 남으시는 분..-_ㅜ;</title>
</post>
