<?xml version="1.0" encoding="UTF-8" standalone="yes"?>
<post>
    <author>신덕현</author>
    <comments/>
    <content>"너 한번 웃겨봐" &lt;br&gt;&lt;br&gt;아무리 잘 웃기는 사람도 맨 정신에 그것도 백주 대낮에 웃겨보라면 십중팔구 &lt;br&gt;&lt;br&gt;당사자 : 네? 지금요? 여기서요? 라고 대답한다. 개그맨도 예외일 순 없다. &lt;br&gt;&lt;br&gt;그래서, 예전에는 유능한 PD일수록 보너스가 나오든지 하면 사재를 털어 재능이 있어 보이는 연기자를 술집으로 데려가는 경우가 종종 있었다. &lt;br&gt;&lt;br&gt;술이 한잔 들어가고 어색함도 덜 해지고, 특히 '동원 방청객'보다 더 잘 웃어주는 술집아가씨들까지 있으면 자신의 재량을 마음껏 발휘들을 하곤 했다. &lt;br&gt;&lt;br&gt;****************************************************************&lt;br&gt;&lt;br&gt;현재 KBS에 재직중인 조의진 본부장이 프로듀서 시절, 김형곤이 갓 데뷔했다. &lt;br&gt;&lt;br&gt;혀가 짧아 대사 전달은 안됐지만 조PD 눈에는 탁월한 능력이 엿보여 박봉을 털어 술집에 갔다. &lt;br&gt;&lt;br&gt;1시간쯤 흘렀을까 밴드가 들어 왔고 &lt;br&gt;&lt;br&gt;조PD : 형곤씨 노래 좀 해 보지. 혀 짧은 사람 노래는 어떤가....? &lt;br&gt;김형곤 : 네! &lt;br&gt;&lt;br&gt;필자도 현장이 있었지만 당시 최고 가수인 패티김, 윤복희의 히트곡을 완벽하게 100% 모창으로 열창을 했다. 거기다가 김형곤은 그날 애드리브(즉흥으로 떠 올리는 아이디어나 연기)까지 선보였다 &lt;br&gt;&lt;br&gt;&lt;br&gt;야한 얘기를 하고 있었는데 &lt;br&gt;&lt;br&gt;김형곤 : 조 PD님. 어제 이발소에 갔었거든요? &lt;br&gt;조PD : 근데?? &lt;br&gt;&lt;br&gt;지금은 거의 사라졌지만 그때는 퇴폐 이발소가 성행을 이루고 있었다. &lt;br&gt;&lt;br&gt;김형곤 : 면도를 끝내고 계속 안마를 하더니요. &lt;br&gt;&lt;br&gt;아가씨가 "스폐셜 마사지 해 드릴까요?" &lt;br&gt;&lt;br&gt;그래서 " 아닸어요.(알았어요.)그랬더니 바지를 내리데요. &lt;br&gt;&lt;br&gt;일동 : (눈이 빛나고) &lt;br&gt;&lt;br&gt;김형곤 : 손으로 뭘 하고 있는데 느낌이 이상한 거예요. 그래서 눈을 번쩍 떴더니 남자인 이발사가 제 그걸 잡고 있는거예요. &lt;br&gt;&lt;br&gt;일동 : 그래서... &lt;br&gt;김형곤 : 그래서... "당신 뭐야?" 그랬더니 글쎄... &lt;br&gt;&lt;br&gt;"손이 모자라서요!" 이러는 거 있죠. &lt;br&gt;&lt;br&gt;애드리브가 강하다는 건 그만큼 순발력이 뛰어나다는 증거다. &lt;br&gt;&lt;br&gt;그날 이후 김형곤은 스타대열에 합류를 시작했다. &lt;br&gt;&lt;br&gt;**********************************************************&lt;br&gt;&lt;br&gt;서세원도 마찬가지다.&amp;nbsp;&amp;nbsp;&lt;br&gt;&lt;br&gt;현재 울산 MBC 신종인 사장이 &amp;lt;청춘만세&amp;gt;PD시절 술집에 갔다. &lt;br&gt;&lt;br&gt;개다리 춤을 추며 '프라우드 메리'란 노래밖에 부른적이 없던 서세원이 아가씨들의 호응 이 커지자 '산 할아버지'를 얼떨결(?)에 부르게 됐다. &lt;br&gt;&lt;br&gt;&lt;br&gt;서세원 :(노래) 산할아버지 나무를 하다가… &lt;br&gt;&lt;br&gt;애드리브를 안 할 인간이 아니었다. &lt;br&gt;&lt;br&gt;서세원:(계속) 잘못해서 X지를 짤렸네. (중략) &lt;br&gt;&lt;br&gt;울고 있는데 산신령이 나타나 &lt;br&gt;&lt;br&gt;금 X지가 네놈의 X지냐? &lt;br&gt;&lt;br&gt;은 X지가 네놈의 X지냐? &lt;br&gt;&lt;br&gt;아닙니다. 제 X지는 거머죽죽 살 X지. &lt;br&gt;&lt;br&gt;그 노래는 12절까지 계속됐다. &lt;br&gt;&lt;br&gt;/방송작가 &lt;br&gt;</content>
    <postId>C86311E0-5D32-47C9-8A77-F53D89E35FEB</postId>
    <pubDate>2003-04-28T00:00:00-04:00</pubDate>
    <title>[임기홍의 함 웃어보자] 이발소서 마사지…눈떠 보니 이발사가</title>
</post>
