<?xml version="1.0" encoding="UTF-8" standalone="yes"?>
<post>
    <author>요즘</author>
    <comments/>
    <content>우연히 2007학년도 대학랭킹을 보니&lt;br&gt;작년과는 많은 차이가 있네요.&lt;br&gt;&lt;br&gt;글로브 앤 메일이라는 대학랭킹을 보면&lt;br&gt;http://www.theglobeandmail.com/reportcard &lt;br&gt;다음과 같습니다.&lt;br&gt;&lt;br&gt;&lt;br&gt;OVERALL EDUCATION &lt;br&gt;(GRADE: A) Western, Waterloo, McMaster, Queens, Guelph, Wilfred Laurier, Winnipeg, Trent, St. Francis, Nipissing&lt;br&gt;(GRADE: A-) McGill, Carleton, Simon Fraser, Ryerson, Brock&lt;br&gt;(GRADE: B+) U OF T, YORK, MONTREAL, ALBERTA, UBC, CONCORDIA, LAURENTIAN&lt;br&gt;(GRADE: B) CALGARY &lt;br&gt;&lt;br&gt;웨스턴온태리오가 1위로 등극하였고요&lt;br&gt;그다음 워터루, 그러나 회사에서 보는 랭킹은&lt;br&gt;다음과 같습니다,(참고로 저희 회사 규모는 캐나다 매이저 회사 중 하나로&amp;nbsp;&amp;nbsp;40,000명을 직원으로 가지고 있구요)&lt;br&gt;&lt;br&gt;1.웨스턴&lt;br&gt;2.킨즈&lt;br&gt;3.유오아티 &amp;lt;--새로등장, University of Ontario Institute of Technology&lt;br&gt;3.워터루&lt;br&gt;4.맥마스터&lt;br&gt;5.욕&lt;br&gt;6.유오브티&lt;br&gt;&lt;br&gt;자세한 평가사항은 생략합니다.&lt;br&gt; </content>
    <postId>F1C0820A-8BB0-4851-85E5-6AA25DC3D10B</postId>
    <pubDate>2007-10-24T00:00:00-04:00</pubDate>
    <title>요즘 대학 랭킹 -학생분께</title>
</post>
