<?xml version="1.0" encoding="UTF-8" standalone="yes"?>
<post>
    <author>Steven</author>
    <comments/>
    <content>Canada 나이아가라 폭포( Niagara Falls )의 한인이 경영하는 Motel을 소개합니다.&lt;br&gt;&lt;br&gt;캐나다에 사는 교포라면 누구나 1년에 몇번은 찾아보는 나이아가라 폭포.&lt;br&gt;봄이면 아직 미쳐 녹지못한 눈위로, 물보라를 일으키며 떨어지는 웅장한 폭포의 무지개가 좋구요.&lt;br&gt;여름이면 볼거리, 먹거리, 탈거리가 즐비하여 밤을 모르고 불야성을 이루는 살아있는 폭포가 좋구요.&lt;br&gt;가을이면 나뭇잎이 뒹구는 Parkway를 따라 폭포를 여유롭게 감상할 수 있는 평화로움이 좋구요.&lt;br&gt;겨울이면 폭포가 내뿜는 물보라에 얼음꽃으로 변한 주변을 따라 X-mas light show가 좋구요.&lt;br&gt;사계절에 따라 다른 모습의 폭포가 좋습니다.&lt;br&gt;이 폭포에서 걸을 수 있는 거리에 한인이 경영하는 Stardust Inn 모텔이 한인여러분을 기다립니다.&lt;br&gt;&lt;br&gt;우리 Stardust Inn 모텔은요...&lt;br&gt;- 깨끗함은 물론이고요. (7년된 새건물)&lt;br&gt;- 교통편 좋구요.(QEW &amp; Hwy420 에서 나오자 마자, 폭포주변 Attractions까지 걸어서 10분)&lt;br&gt;- 가격 저렴하구요.(폭포근처의 비싼 숙박비에 기절했던 분들, 한인교민여러분들에게는 무조건 당일 Rate에 20% DC 프로그램-전화예약시)&lt;br&gt;- 아침식사포함하구요.(Summer Season 매일, 기타 Season 토,일,휴일아침)&lt;br&gt; &lt;br&gt;이런분들 환영합니다.&lt;br&gt;- 모국에서 부모님이나 친지방문으로 폭포에 오시는 분들 (Family Suit를 추천합니다)&lt;br&gt;- 가족이나 친구와 함께 폭포에 오시는 분들 (Double Bed Room을 추천합니다)&lt;br&gt;- 연인이나 부부가 색다른 분위기를 연출하여 사랑을 업그레이드하길 원하는 분들 (Jacuzzi Room을 추천합니다. 비밀보장)&lt;br&gt;- 홀로 배낭여행이나 홀로 현지답사, 출장오시는 분들 (Single Room을 추천합니다)&lt;br&gt;- 폭포근처의 비싼 숙박비가 부담스러워, 운전이 피곤해도 당일치기로 관광오셨던 분들...&lt;br&gt;- 모텔이 미덥지 못해 비싼 돈주고 호텔에서 묶었던 분들...(솔직히 Sheraton 이나 Hilton 보다는 못합니다) &lt;br&gt;&lt;br&gt;&lt;br&gt;오셔서 직접 확인해보세요.&lt;br&gt;전화예약 : 1-800-532-1588&lt;br&gt;&amp;nbsp;&amp;nbsp;&amp;nbsp;&amp;nbsp;&amp;nbsp;&amp;nbsp;&amp;nbsp;&amp;nbsp;&amp;nbsp;&amp;nbsp; 905-371-2160&lt;br&gt;Web : http://www.stardustinn.ca &lt;br&gt;E-mail : stardust_inn@yahoo.ca &lt;br&gt;Address : 5528 Buchannan Ave. Niagara Falls, Ontario</content>
    <postId>97A823B4-C571-480D-A751-BAADDCD4B167</postId>
    <pubDate>2008-09-10T00:00:00-04:00</pubDate>
    <title>Canada 나이아가라 폭포의 한인이 경영하는 Motel</title>
</post>
