<?xml version="1.0" encoding="UTF-8" standalone="yes"?>
<post>
    <author>comm</author>
    <comments>
        <comment>
            <author>ace5</author>
            <date>2010-05-26T00:00:00-04:00</date>
            <content>it's great golf course !!! --- 강추^^^</content>
        </comment>
        <comment>
            <author>배길상</author>
            <date>2010-05-26T00:00:00-04:00</date>
            <content>꼭 참석하고 싶은데 시간이 시간이 맞지가 않네요. 즐 골프 하세요 ^_^......</content>
        </comment>
        <comment>
            <author>배길상</author>
            <date>2010-05-26T00:00:00-04:00</date>
            <content>저런 오타네요. "시간이 시간이" 를 "시간이" 로 정정 합니다.</content>
        </comment>
        <comment>
            <author>graham</author>
            <date>2010-05-27T00:00:00-04:00</date>
            <content>참석함니다.</content>
        </comment>
        <comment>
            <author>comm</author>
            <date>2010-05-27T00:00:00-04:00</date>
            <content>빨리 신청하세요 1분^.^ 남았습니다.</content>
        </comment>
    </comments>
    <content>토너먼트 수고하신 회원분들을 위한 벙개 있습니다.&lt;br&gt;&lt;br&gt;일시: 5월 29일 (토) 2시.&lt;br&gt;비용: $49 + 걷기&lt;br&gt;인원: 4명 (jay song &amp; comm 2명은 참가확정)&lt;br&gt;장소: Tangle Creek Gc http://www.tanglecreekgolf.com/&lt;br&gt;참석: 선착순 2명 모집합니다. 가능하신 분들은 목요일 (5월 27일) 까지 댓글 (전화번호/메일주소) 달아주세요.</content>
    <postId>2CDC5C1F-1C4F-4711-89B9-DFC0C7C098C1</postId>
    <pubDate>2010-05-25T00:00:00-04:00</pubDate>
    <title>5월 벙개 모임</title>
</post>
