<?xml version="1.0" encoding="UTF-8" standalone="yes"?>
<post>
    <author>허현옥</author>
    <comments>
        <comment>
            <author>SP Nam</author>
            <date>2010-04-18T00:00:00-04:00</date>
            <content>감사합니다~. 세미나도 매우 유익했고 좋은 시간이였습니다.</content>
        </comment>
        <comment>
            <author>김형태</author>
            <date>2010-04-21T00:00:00-04:00</date>
            <content>수고많으셨네요. 좀 더웠죠. 시원한 물을 준비하면 좋겠다는...</content>
        </comment>
    </comments>
    <content>세미나 자료 입니다.&lt;br&gt;&lt;br&gt;http://www.iceup.org/files/project44/COSKA_2010_Android_Part1.ppt&lt;br&gt;&lt;br&gt;http://www.iceup.org/files/project44/HelloAndroid_ListViewTutorial.zip</content>
    <postId>9745FAC9-E2A0-4F85-BD3D-AB4F2CE80900</postId>
    <pubDate>2010-04-17T00:00:00-04:00</pubDate>
    <title>Android Seminar Part1 - 세미나 자료</title>
</post>
