<?xml version="1.0" encoding="UTF-8" standalone="yes"?>
<post>
    <author>김중수</author>
    <comments/>
    <content>당사는 삼성전자 캐나다 법인의 Authorized Service Centre로서 TV In-Home서비스와 RMA Return, RB 제품에 대한 Wholesale을 담당하고 있습니다. 아래와 같이 Programmer를 모집하오니 합법적으로 Canada에서 취업할 수 있는 분으로서 관심 있으신 분들의 많은 지원을 바랍니다.  &#xD;
&#xD;
 &#xD;
&#xD;
회사명:                KOAMBRA CANADA, INC.&#xD;
&#xD;
근무지:                Mississauga (Kennedy Road &amp; Courtneypark Drive E.)&#xD;
&#xD;
근무시간:           월요일 – 금요일, 8:30 am – 5:00 pm (Lunch Break: 12:30 – 1:00 pm)&#xD;
급여:                     인터뷰시 협의 예정임&#xD;
&#xD;
BENEFIT PLAN:  한식 Lunch Catering 금액보조&#xD;
&#xD;
                    입사후 3개월 경과시점부터 Group RRSP 보조&#xD;
&#xD;
지원방법:           이메일 ashleykim@koambracanada.com 으로 Resume 송부&#xD;
&#xD;
 &#xD;
&#xD;
PROGRAMMER &#xD;
&#xD;
담당 업무:    회사 Process에 관한 Programming / Data 관리, Upload 및 분석&#xD;
&#xD;
자격 요건:    Language (특히 C+ or C# / Visual Basic 6.0 / Visual Studio / ASP.NET / PHP) 가능자 우대&#xD;
                                MS SQL Query와 MS Office에 능숙하신분</content>
    <postId>0297409A-1007-4381-9F38-8F8C9CAECFB2</postId>
    <pubDate>2011-04-19T00:00:00-04:00</pubDate>
    <title>Programmer - KOAMBRA CANADA, INC</title>
</post>
