<?xml version="1.0" encoding="UTF-8" standalone="yes"?>
<post>
    <author>황성규</author>
    <comments>
        <comment>
            <author>황성규</author>
            <date>2004-06-30T00:00:00-04:00</date>
            <content>단체사진등 몇장 추가되었습니다.</content>
        </comment>
    </comments>
    <content>&lt;a href="http://f1.pg.photos.yahoo.com/ph/community_one/album?.tok=phP7sVBB1baRESQE&amp;.dir=/d1ab&amp;.src=ph" target="_blank"&gt;여기를 눌러주세요&lt;/a&gt;&lt;br&gt;&#xD;
&#xD;
고화질의 원본은 고상호씨께 있습니다.&#xD;
</content>
    <postId>24CE547B-3BD6-4205-BE77-FFB72DD5C692</postId>
    <pubDate>2004-06-29T00:00:00-04:00</pubDate>
    <title>사진나왔습니다.</title>
</post>
