<?xml version="1.0" encoding="UTF-8" standalone="yes"?>
<post>
    <author>권상하</author>
    <comments>
        <comment>
            <author>권상하</author>
            <date>2010-01-31T00:00:00-05:00</date>
            <content>소로스가 오래전에 3번 째 부인으로 엄청난 미모의 30세 연하 재미 한인 바이올리니스트와 결혼했는데, 이제 소로스는 70이 넘었으니, 아직 미혼이거나 혼자 이신 분들은 관심을 가져 보시길</content>
        </comment>
    </comments>
    <content>소로스가 연설문에서, 오바마의 금융기관 규제는 잘한 것이긴 하지만 좀 성급했다,, 고 했는데, &#xD;
잘 한 일 이라고 했으니, 금융기관 규제는 그대로 할 것 같고.. &#xD;
성급하다고 했으니, 주식은 하락 할 것이고,&#xD;
소로스는 그 틈을 이용해서 한껀 하겠지요&#xD;
&#xD;
by 명사십리</content>
    <postId>43CCDD91-DA3A-407B-A068-54A1127A86E1</postId>
    <pubDate>2010-01-31T00:00:00-05:00</pubDate>
    <title>명사십리의 견해 요약</title>
</post>
