<?xml version="1.0" encoding="UTF-8" standalone="yes"?>
<post>
    <author>이홍식</author>
    <comments/>
    <content>18:00 - 20:00 로 해 주셨으면 좋겠습니다 :-)&#xD;
&#xD;
이계영 wrote:&#xD;
&gt; &lt;b&gt;강좌명 :&lt;/b&gt; XML 및 관련 기술&#xD;
&gt;  &#xD;
&gt; &lt;b&gt;내용: &lt;/b&gt; XML과 그와 관련된 기술에 대해 다루며 동시에 IBM에서 실시하는 Professional Certification Program의 XML and Related Technologies 자격증 시험에 대비&#xD;
&gt;  &#xD;
&gt; &lt;b&gt;Session 1- Design&lt;/b&gt;&#xD;
&gt; XML의 디자인시 고려사항&#xD;
&gt; W3C 권고안의 Syntax와 세부사항(XML, XSL, DOM, XPath, DTD)&#xD;
&gt;  &#xD;
&gt; &lt;b&gt;Session 2- Information Modeling&lt;/b&gt;&#xD;
&gt; 데이터/문서의 구조 분석&#xD;
&gt; XML형태로의 표현&#xD;
&gt; DTD, XML Schema&#xD;
&gt;  &#xD;
&gt; &lt;b&gt;Session 3- XML Processing&lt;/b&gt;&#xD;
&gt; SAX/DOM&#xD;
&gt;  &#xD;
&gt; &lt;b&gt;Session 4- XML Transformation/Query&lt;/b&gt;&#xD;
&gt; XSLT, XSL, XPath, XLink&#xD;
&gt; &#xD;
&gt; &lt;b&gt;대상: &lt;/b&gt; 데이터프로세싱 프로그램 경험과 기본적인 자바 프로그램 작성을 해보신 분.&#xD;
&gt; &lt;b&gt;일시: &lt;/b&gt; 11월 매주 일요일(11월11일 부터) 15:00 ~ 17:00 또는 18:00 ~ 20:00(추후 협의 가능)&#xD;
&gt; &lt;b&gt;강사:&lt;/b&gt;이계영 905 785-6301 (XML and Related Technologies 자격증 기 취득)&#xD;
&gt; &lt;b&gt;장소: &lt;/b&gt; 이계영 자택(확정후 정확한 약도 게시예정)&#xD;
&gt; &lt;b&gt;강의료: &lt;/b&gt; 한세션당 25$&#xD;
&gt; &lt;b&gt;최소참여인원:&lt;/b&gt; 3명&#xD;
&gt; &#xD;
&gt; 수강 희망자: ( 11월 4일 마감, 패스워드는 1 )&#xD;
&gt; 1) 최익준 416-488-2561 michael00@sympatico.ca(월/화/목 가능) &lt;font color="blue"&gt;Toronto/NorthYork 카풀 가능&lt;/font&gt;&#xD;
&gt; 2) 강윤정 905-848-4565 okid88@yahoo.com(화요일 제외한 다른날 가능)&#xD;
&gt; 3) 이홍식 416-292-9774 brianhsklee@yahoo.com (일요일 저녁 가능)&#xD;
&gt; 4)&#xD;
&gt; 5)&#xD;
&gt; 6)&#xD;
&gt; 7)&#xD;
&gt; 8)&#xD;
&gt; 9)&#xD;
&gt; 10)&#xD;
&gt; 11)&#xD;
&gt; 12)&#xD;
&gt; &#xD;
&gt; &#xD;
&gt; &#xD;
&gt; &#xD;
&gt; 다음은 자격증에 대한 장점을 기술한 내용(IBM사이트에서 가져옴)&#xD;
&gt; &#xD;
&gt; &lt;b&gt;Overview: Benefits&#xD;
&gt; Certification is a tool to help objectively measure the performance of a professional on a given job at a defined skill level. Certification, therefore, is beneficial for individuals who wish to validate their own skills and performance levels and/or their employees. For optimum benefit, the certification tests must reflect the critical tasks required for a job, the skill levels of each task, and the frequency by which a task needs to be performed. IBM prides itself in designing comprehensive, documented processes which ensure that IBM certification tests remain relevant to the work environment of potential certification candidates. &lt;/b&gt;&#xD;
&gt; In addition to assessing job skills and performance levels, professional certification may also provide benefits such as:&#xD;
&gt; ·	For employees: &#xD;
&gt; o	Promotes recognition as an IBM certified professional &#xD;
&gt; o	Helps create advantages in interviews &#xD;
&gt; o	Assists in salary increases and/or corporate advancement &#xD;
&gt; o	Increases self esteem &#xD;
&gt; o	Provides continuing professional benefits &#xD;
&gt; IBM의 자격증 관련 사이트: http://www-1.ibm.com/certify/index.shtml&#xD;
&gt; </content>
    <postId>6CEF89C2-5499-4EF7-8437-3914A00CC908</postId>
    <pubDate>2001-11-04T00:00:00-05:00</pubDate>
    <title>RE: &lt;b&gt;XML 강좌  (일요일로 변경)&lt;/b&gt;</title>
</post>
