<?xml version="1.0" encoding="UTF-8" standalone="yes"?>
<post>
    <author>황성규</author>
    <comments>
        <comment>
            <author>황선용</author>
            <date>2003-01-30T00:00:00-05:00</date>
            <content>홍영기씨...진심으로 축하드립니다. 고생 끝 행복 시작!!</content>
        </comment>
        <comment>
            <author>홍영기</author>
            <date>2003-01-30T00:00:00-05:00</date>
            <content>커뮤니티원 모든 분들 덕분에 잘 된 것 같습니다. 정말로 감사합니다. </content>
        </comment>
    </comments>
    <content>홍영기씨가 드디어 2월달부터 퍼머넌트로 일을 하게되었습니다.&#xD;
축하합니다.&#xD;
&#xD;
앞으로 이런 좋은소식이 많이 들려오길 기원합니다.&#xD;
&#xD;
</content>
    <postId>7EDE5834-3C6B-457F-8370-423640C09106</postId>
    <pubDate>2003-01-30T00:00:00-05:00</pubDate>
    <title>축하합니다.</title>
</post>
