<?xml version="1.0" encoding="UTF-8" standalone="yes"?>
<post>
    <author>김중수</author>
    <comments/>
    <content>제가 다니는 회사에서 가끔 할인 입장권을 판매하더군요.&#xD;
지난번에도 Wonder Land 40%할인권이 나와 다녀왔습니다.&#xD;
이번에는 MarineLand 군요.&#xD;
&#xD;
TV에서 선전하는 고래나오는 Marineland입니다. 바로 나이가라폭포옆에 있지요. 재미있는 놀이기구들과 아이들이 좋아 할만한 것들이 많이 있구요..주말 가족과 함께 할수 있는 인기있는 놀이공원입니다. 할인권이 필요하신 분은 연락주세요..&#xD;
제가 구해볼께요.&#xD;
&#xD;
(사용날짜) 한정 : &#xD;
       June 15, June 16, June 17, 2001 (금,토,일)&#xD;
       금액 :&#xD;
       성인 (5세 이상) : 14$  (정상요금은 아마 30$가까이..)&#xD;
            (4세 미만) : 무료.&#xD;
       위치 : 나이아가라 폭포 옆.&#xD;
</content>
    <postId>9C13F9D7-9BE5-4538-8610-456AD91EE95A</postId>
    <pubDate>2001-06-01T00:00:00-04:00</pubDate>
    <title>Marine Land 할인 입장권 필요하신분.</title>
</post>
