<?xml version="1.0" encoding="UTF-8" standalone="yes"?>
<post>
    <author>황성규</author>
    <comments/>
    <content>저도 윤정씨랑 똑같은 생각을 했습니다.&#xD;
&#xD;
강윤정 wrote:&#xD;
&gt; 순간 머리에 스치는 생각은.. 이건 interface쓰면 해결되지 않나..&#xD;
&gt; 하는 -_-;&#xD;
&gt; &#xD;
&gt; 1. 매년 바뀔 tax calculation class를 감싸는 interface 생성&#xD;
&gt; 2. 1의 interface를 implement하는 당해년도 specific tax class 생성&#xD;
&gt; 3. 특정 tax class를 생성하는 factory class 만들고, 그&#xD;
&gt;  factory class는 외부 property file로부터 생성시킬 특정&#xD;
&gt;   class name을 읽어들여서 tax object 만들어 return.&#xD;
&gt; 4. caller class는 interface의 method getTax()만 call.&#xD;
&gt; 5. 당해년도의 바뀐 tax class를 포함한 jar file로 production  site에 deploy.&#xD;
&gt; &#xD;
&gt; 물론 tax calculation의 상당부분이 동일하고&#xD;
&gt; 차이점을 external화 할 수 있다면 XML을 써서 해도 좋겠고..&#xD;
&gt; 공통계산 부분 class를 만들고&#xD;
&gt; 당해년도 specific 부분을 떼어서 따로 class를 만든다면..&#xD;
&gt; XML을 쓰지 않더라도 가능할 것 같은데요.&#xD;
&gt; &#xD;
&gt; &#xD;
&gt; &#xD;
&gt; &#xD;
&gt; &#xD;
&gt; &#xD;
&gt; </content>
    <postId>C935B6AA-8CB1-40D1-A7AE-6EB4484615E0</postId>
    <pubDate>2001-10-16T00:00:00-04:00</pubDate>
    <title>I like your idea.</title>
</post>
