<?xml version="1.0" encoding="UTF-8" standalone="yes"?>
<post>
    <author>김경용</author>
    <comments>
        <comment>
            <author>고상호</author>
            <date>2010-12-17T00:00:00-05:00</date>
            <content>감축드립니다.</content>
        </comment>
    </comments>
    <content>어제 (12월16일) 조촐하지만 즐거운 컴원의 2010년 송년회가 잘 마무리되었습니다.&#xD;
&#xD;
참석해주신 고상호선배님, 정미영회장님, 허현옥씨, 심성준씨 모두 감사드립니다.&#xD;
&#xD;
위에 잠시 언급(?)했듯이, 참석인원들의 전원동의와 적극적인 추대, 사실 모임전에 고상호전회장님의 지혜로운 자문과 나름대로 충분히 심사숙고한 결과로, 2011년 저희 컴원을 새롭게 이끌어주실 최초의 여성회장님을 모시게 되었습니다.&#xD;
&#xD;
송년회에서 주제되었던, 저희 모임의 새로운 변혁을 꿈꾸면서 새해에는 참신한 아이디어와 적극적인 참여로, 모두에게 항상 그래왔었던 좋은 모임으로 거듭나는 계기가 될 것을 기원합니다.&#xD;
&#xD;
다시한번 정미영회장님의 선출을 진심으로 축하드립니다.</content>
    <postId>ED8A9174-1225-48E8-982E-9C3ABD797F82</postId>
    <pubDate>2010-12-17T00:00:00-05:00</pubDate>
    <title>&lt;font color=blue size=10&gt;축!!! 정미영신임회장 선출&lt;/font&gt;</title>
</post>
