<?xml version="1.0" encoding="UTF-8" standalone="yes"?>
<post>
    <author>샘 권</author>
    <comments/>
    <content>수필가 최원현 씨가 한국가정사역연구소가 발행하는 '행복한 우리 집'에서 "우리가 행복해야 하는 9가지 이유"를 제시했다. &#xD;
&#xD;
하나, &#xD;
당신의 냉장고에 음식이 있고 &#xD;
당신의 등에 옷이 걸쳐 있으며 비바람을 막을 지붕이 있고 &#xD;
잠 잘 곳이 있다면 &#xD;
당신은 지구상의 75%의 사람들보다 부유합니다. &#xD;
&#xD;
둘, &#xD;
만약 당신의 은행계좌나 지갑에 돈이 있고 &#xD;
얼마의 동전이 접시에 담겨있다면 &#xD;
당신은 이 세상의 8%의 부유층에 속합니다. &#xD;
&#xD;
셋, &#xD;
만약 당신이 오늘 아침에 병들지 아니한 자로 일어났다면 &#xD;
당신은 이번주를 넘기지 못하는 &#xD;
수백만명의 사람들보다 축복 받았습니다. &#xD;
&#xD;
넷, &#xD;
만약 당신이 전쟁의 위험을 경험한 적이 없고 &#xD;
외로운 감옥생활을 해보지 않았으며 &#xD;
고문의 괴로움을 맛보지 않고 &#xD;
배고픔의 고통이 없었다면 &#xD;
당신은 지금 이 순간 고통을 당하는 &#xD;
또 다른 500만명 보다 낫습니다. &#xD;
&#xD;
다섯, &#xD;
만약 당신이 체포 고문 혹은 죽음의 위험이 없이 &#xD;
교회에 갈 수 있다면 &#xD;
당신은 세계 30억명의 사람들보다 축복 받았습니다. &#xD;
&#xD;
여섯, &#xD;
만약 당신의 부모 모두가 살아 계시고 &#xD;
이혼하지 않았다면 미국에서 조차 당신은 드문 예입니다. &#xD;
&#xD;
일곱, &#xD;
만약 당신이 미소를 머금은 채 머리를 들고 &#xD;
진정으로 감사할 수 있다면 당신은 축복 받은 사람입니다. &#xD;
오직 성숙한 사람만이 그럴 수 있으며 &#xD;
대부분의 사람은 그러하지 못하기 때문입니다. &#xD;
&#xD;
여덟, &#xD;
만약 오늘 당신이 누군가와 손은 맞잡을 수 있고 &#xD;
포옹할 수 있으며 어깨를 두드려줄 수 있다면 &#xD;
당신은 축복 받은 사람입니다. &#xD;
왜냐하면 당신은 치유의 손길을 줄 수 있기 때문입니다. &#xD;
&#xD;
아홉, &#xD;
만약 당신이 당신의 안녕을 생각하고 있는 사람이 &#xD;
보낸 글을 읽을 수 있다면 &#xD;
당신의 축복은 곱절이나 더합니다. &#xD;
아니 그 이상일 것입니다. &#xD;
왜냐하면 지구상에는 글을 전혀 읽지 못하는 사람이 &#xD;
20억 명 이나 있습니다. &#xD;
&#xD;
이제 당신은 행복하시죠? &#xD;
&#xD;
</content>
    <postId>F3B3129C-CC8B-4A3C-AA95-F2B1FD2015E1</postId>
    <pubDate>2004-12-05T00:00:00-05:00</pubDate>
    <title>퍼온글</title>
</post>
