<?xml version="1.0" encoding="UTF-8" standalone="yes"?>
<post>
    <author>이홍식</author>
    <comments/>
    <content>bellwether \BEL-wether\, noun:&#xD;
1. A wether, or sheep, which leads the flock, with a bell on his neck.&#xD;
2. Hence: A leader of a movement or activity. &#xD;
&#xD;
Bellwether is a compound of bell and wether, a male sheep, usually castrated. Wether is related to Latin vetus, veteran.&#xD;
방울과 양이라는 단어가 합쳐져 만들어진 단어인데, 거세된 숫양이 방울을 달게 되는데 양무리를 이끄는 우두머리양을 bellwether라 하며 지도자, 선두주자라는 의미로 확대되었음. &#xD;
&#xD;
야후사전...&#xD;
bell·weth·er &#xD;
－ n.&#xD;
1 (양떼를 이끄는) 방울 달린 양.&#xD;
2 지도[선도]자; 주모자, 장본인.&#xD;
&#xD;
&#xD;
"Because Yahoo is first out of the gate and since it is the largest Internet search service, investors and analysts see it as a bellwether for the fledgling (갓 시작된, 풋나기) Internet industry." -- Reuters, July 6, 1999&#xD;
&#xD;
야후가 (인터넷 사업이라는)문을 젤 먼저 뛰쳐나왔을 뿐만아니라  인터넷 검색서비스로는 최대의 업체인지라 투자가들, 분석가들은 그를 이제 기지개를 피는 새로운 인터넷 사업의 선두주자로 주시하고 있다.&#xD;
 &#xD;
</content>
    <postId>F4B50580-AEAF-4CEE-AF44-64483BD35055</postId>
    <pubDate>2002-10-21T00:00:00-04:00</pubDate>
    <title>bellwether </title>
</post>
