<?xml version="1.0" encoding="UTF-8" standalone="yes"?>
<post>
    <author>정순화</author>
    <comments>
        <comment>
            <author>박재홍</author>
            <date>2006-04-25T00:00:00-04:00</date>
            <content>여기가 어디쯤이죠?</content>
        </comment>
        <comment>
            <author>허현옥</author>
            <date>2006-04-25T00:00:00-04:00</date>
            <content>아...맥주 한 캔 살 돈이 없어서 경치 구경을 못하겠군요...^^;;;;</content>
        </comment>
        <comment>
            <author>이상윤</author>
            <date>2006-04-26T00:00:00-04:00</date>
            <content>우와..영화에서 나오는 장면 같아요...</content>
        </comment>
        <comment>
            <author>정순화</author>
            <date>2006-04-26T00:00:00-04:00</date>
            <content>Bathurst 상에 있는 아파트입니다. steel 쪽에 가깝게 있는데, North York 빌딩들이 쫘악 보인다지요. 저기 켈리집도 보이지요?&lt;br&gt;&lt;br&gt;ㅋㅋ... 제가 맥주 한캔 대접할테니 오세요. 단, 월급타면 이자붙어서 한박스입니다.</content>
        </comment>
        <comment>
            <author>Kelly J Lee</author>
            <date>2006-04-26T00:00:00-04:00</date>
            <content>우와~~~~~~~멋있어요. 겨울 경치도 볼만한걸요?&lt;br&gt;우리집? ㅋㅋㅋ&lt;br&gt;&lt;br&gt;맥주 한캔만? 안주도 주는거죠? 들고 가야하나요? ^___^</content>
        </comment>
        <comment>
            <author>정순화</author>
            <date>2006-04-27T00:00:00-04:00</date>
            <content>멸치에 고추장 OK?</content>
        </comment>
        <comment>
            <author>오승준</author>
            <date>2006-04-27T00:00:00-04:00</date>
            <content>저번사진은 온도가 있고, 이번 사진은 소리가?</content>
        </comment>
        <comment>
            <author>심용해</author>
            <date>2006-04-28T00:00:00-04:00</date>
            <content>와우...시원합니다..광각이 시원하게 잡혔어요...</content>
        </comment>
    </comments>
    <content>주말내내 비가 오더니 하루가 다르게 초록이들이 쑥쑥 올라오네요.&lt;br&gt;저희 아파트에서 찍어본 사진입니다. 겨울의 삭막했던 경치가 이렇게 이쁘게 변해가네요. 좋은 경치가 필요하신 분은 언제든지 방문 환영합니다.&lt;br&gt;단, 입장료는 맥주 한 캔입니다. ㅋㅋㅋ</content>
    <postId>0AABA1F0-1AB5-46F4-9A58-3196C67BE473</postId>
    <pubDate>2006-04-25T00:00:00-04:00</pubDate>
    <title>봄이 오는 소리</title>
</post>
