<?xml version="1.0" encoding="UTF-8" standalone="yes"?>
<post>
    <author>최봉준</author>
    <comments>
        <comment>
            <author>오승준</author>
            <date>2007-01-20T00:00:00-05:00</date>
            <content>저도 캐논 카메라인데 정말 유용한 정보 감사합니다.</content>
        </comment>
        <comment>
            <author>심용해</author>
            <date>2007-01-21T00:00:00-05:00</date>
            <content>잘됐네요..청소 꼭 받고 좋은 사진 많이 찍으세요...^^ &lt;br&gt;전 니콘이라 좀 이곳에서 청소는 못받을것 같고, 니콘 as 알아봐야 겠어요..^^</content>
        </comment>
        <comment>
            <author>허현옥</author>
            <date>2007-01-24T00:00:00-05:00</date>
            <content>오호..좋은 소식이네요. 감사</content>
        </comment>
    </comments>
    <content>안그래도 CCD에 먼지가 낀것 같긴했는데, 확실치 않다가 심용해씨가 정확히 지적해주셔서 청소하기로 결심을 했죠. 혼자 해볼까도 했는데, 여기저기 글을 보니 너무들 겁을 주더라구요. 잘못하다보면 카메라 버려야된다는 둥.. 쩝. 헨리스에 맡기면 50불은 받는 다는 둥. 눈앞이 캄캄...&lt;br&gt;&lt;br&gt;다행히도 여기 저기 알아보다 캐논 카메라면 미시사가에 있는 캐논 서비스 센타에서 공짜로 청소를 해준다는 야그를 듣고 전화해보니 진짜더라구요. 워런티하고는 상관없이 무조건 캐논 카메라면 공짜라고 하더군요. &lt;br&gt;&lt;br&gt;혹시 캐논 카메라 가진분들은 청소 걱정은 안해도 될것 같네요. CCD뿐 아니라 전체적으로 미러랑 뷰파인더랑 대충 다 해준다는 군요.&lt;br&gt;www.canon.ca가면 주소랑 전화번호가 있어요.&lt;br&gt;&lt;br&gt;즐사 하세요. 그럼, 또...</content>
    <postId>3D86059C-8E46-4981-AB48-214E93967BE1</postId>
    <pubDate>2007-01-19T00:00:00-05:00</pubDate>
    <title>캐논 카메라 청소 공짜로..</title>
</post>
