<?xml version="1.0" encoding="UTF-8" standalone="yes"?>
<post>
    <author>박재홍</author>
    <comments>
        <comment>
            <author>심용해</author>
            <date>2008-03-18T00:00:00-04:00</date>
            <content>요즘 고드름 멋있죠? 저도 집에서 삼처럼 생긴 고드름 많이 봤거든요..ㅋㅋ</content>
        </comment>
    </comments>
    <content>점심때 보았던 고드름이 저녁때에는 제법 많이 자라있더군요.&amp;nbsp;&amp;nbsp;Looks quite bloody!!!</content>
    <postId>8A1E0D8C-9E5E-4201-BF06-A48FD5D854C5</postId>
    <pubDate>2008-03-09T00:00:00-05:00</pubDate>
    <title>고드름</title>
</post>
